MANIFEST.in
README.rst
setup.py
alexis/__init__.py
alexis/rhel.py
alexis/libs/__init__.py
alexis/libs/clonevirtualenv.py
alexis/libs/virtualenv.py
clever_alexis.egg-info/PKG-INFO
clever_alexis.egg-info/SOURCES.txt
clever_alexis.egg-info/dependency_links.txt
clever_alexis.egg-info/requires.txt
clever_alexis.egg-info/top_level.txt