Metadata-Version: 1.1
Name: clever-alexis
Version: 0.1.1.dev5
Summary: Clever redhead girl that builds and packs Python project with Virtualenv into rpm, deb, etc.
Home-page: https://bitbucket.org/KulaPard/alexis
Author: Taras Drapalyuk (KulaPard)
Author-email: kulapard@gmail.com
License: BSD License
Platform: UNKNOWN
Classifier: Development Status :: 2 - Pre-Alpha
Classifier: License :: OSI Approved :: BSD License
Classifier: Programming Language :: Python
